{
  "totalTvlUSD": 45925073.67,
  "coinsByCoingeckoId": {
    "solana": 76583.706683664,
    "msol": 84055.049636147,
    "bitcoin": 192.66823,
    "ethereum": 182.59689,
    "ftx-token": 23901.301302,
    "serum": 211148.656022,
    "mango-markets": 965510.398396
  },
  "pricesByCoingeckoId": {
    "BTC": 51731,
    "SOL": 203.67,
    "ETH": 4114.51,
    "mSOL": 207.22,
    "FTT": 43.2,
    "SRM": 4.25,
    "USDC": 1,
    "MNGO": 0.27058
  },
  "sharePricesByGlobalId": {
    "mainnet_income_call_sol": 1.02193,
    "mainnet_income_call_marinade": 1.01091,
    "mainnet_income_call_btc": 1.05125,
    "mainnet_income_call_eth": 1.006,
    "mainnet_income_call_ftt": 1,
    "mainnet_income_call_srm": 1,
    "mainnet_income_call_mngo": 1
  }
}