{
  "totalTvlUSD": 110735168.52,
  "coinsByCoingeckoId": {
    "solana": 148456.984807243,
    "msol": 160447.696911253,
    "bitcoin": 414.011568,
    "saber": 20000000,
    "ftx-token": 80516.482903,
    "usd-coin": 15501947.103285,
    "terra-luna": 69091.064243,
    "socean-staked-sol": 10534.660250754,
    "serum": 4033017.937429,
    "mango-markets": 8052294.421679,
    "raydium": 19383.995558,
    "ethereum": 1701.996568
  },
  "pricesByCoingeckoId": {
    "BTC": 42454,
    "SOL": 146.22,
    "ETH": 3250.48,
    "mSOL": 150.02,
    "FTT": 41.89,
    "SRM": 3.11,
    "USDC": 1,
    "MNGO": 0.196249,
    "scnSOL": 150.67,
    "SBR": 0.085706,
    "LUNA": 78.83,
    "RAY": 5.32
  },
  "sharePricesByGlobalId": {
    "mainnet_income_call_sol": 1.04513,
    "mainnet_income_call_marinade": 1.03062,
    "mainnet_income_call_btc": 1.06847,
    "mainnet_income_call_sbr": 1.05102,
    "mainnet_income_call_ftt": 1.02095,
    "mainnet_income_put_mngo": 1.002,
    "mainnet_income_call_luna": 1.02766,
    "mainnet_income_call_socean": 1.01667,
    "mainnet_income_call_srm": 1.01356,
    "mainnet_income_call_mngo": 1.0133,
    "mainnet_income_call_ray": 1.00283,
    "mainnet_income_call_eth": 1.01536,
    "mainnet_income_put_sol": 1.00269,
    "mainnet_income_put_btc": 1.0024
  },
  "depositTokenByGlobalId": {
    "mainnet_income_call_sol": 148456.984807243,
    "mainnet_income_call_marinade": 160447.696911253,
    "mainnet_income_call_btc": 414.011568,
    "mainnet_income_call_sbr": 20000000,
    "mainnet_income_call_ftt": 80516.482903,
    "mainnet_income_put_mngo": 465846.95,
    "mainnet_income_call_luna": 69091.064243,
    "mainnet_income_call_socean": 10534.660250754,
    "mainnet_income_call_srm": 4033017.937429,
    "mainnet_income_call_mngo": 8052294.421679,
    "mainnet_income_call_ray": 19383.995558,
    "mainnet_income_call_eth": 1701.996568,
    "mainnet_income_put_sol": 12664441.18,
    "mainnet_income_put_btc": 2371658.97
  },
  "usdValueByGlobalId": {
    "mainnet_income_call_sol": 21707380.32,
    "mainnet_income_call_marinade": 24070363.49,
    "mainnet_income_call_btc": 17576447.11,
    "mainnet_income_call_sbr": 1714120,
    "mainnet_income_call_ftt": 3372835.47,
    "mainnet_income_put_mngo": 465846.95,
    "mainnet_income_call_luna": 5446448.59,
    "mainnet_income_call_socean": 1587257.26,
    "mainnet_income_call_srm": 12542685.79,
    "mainnet_income_call_mngo": 1580254.73,
    "mainnet_income_call_ray": 103122.86,
    "mainnet_income_call_eth": 5532305.8,
    "mainnet_income_put_sol": 12664441.18,
    "mainnet_income_put_btc": 2371658.97
  },
  "globalIdToDepositTokenCoingeckoId": {
    "mainnet_income_call_sol": "solana",
    "mainnet_income_call_marinade": "msol",
    "mainnet_income_call_btc": "bitcoin",
    "mainnet_income_call_sbr": "saber",
    "mainnet_income_call_ftt": "ftx-token",
    "mainnet_income_put_mngo": "usd-coin",
    "mainnet_income_call_luna": "terra-luna",
    "mainnet_income_call_socean": "socean-staked-sol",
    "mainnet_income_call_srm": "serum",
    "mainnet_income_call_mngo": "mango-markets",
    "mainnet_income_call_ray": "raydium",
    "mainnet_income_call_eth": "ethereum",
    "mainnet_income_put_sol": "usd-coin",
    "mainnet_income_put_btc": "usd-coin"
  }
}