{
  "totalTvlUSD": 67671735.98,
  "coinsByCoingeckoId": {
    "usd-coin": 5889061.748446,
    "saber": 10999999.811266,
    "terra-luna": 9999.429376,
    "socean-staked-sol": 5499.994393146,
    "solana": 83999.999119664,
    "msol": 84999.999992832,
    "bitcoin": 282.182664,
    "ethereum": 586.959694,
    "ftx-token": 28848.108048,
    "serum": 3458959.704526,
    "mango-markets": 2280877.871688
  },
  "pricesByCoingeckoId": {
    "BTC": 47517,
    "SOL": 172.02,
    "ETH": 3748.81,
    "mSOL": 176.2,
    "FTT": 39.46,
    "SRM": 3.49,
    "USDC": 1,
    "MNGO": 0.216347,
    "scnSOL": 175.03,
    "SBR": 0.110439,
    "LUNA": 86.61
  },
  "sharePricesByGlobalId": {
    "mainnet_income_put_sol": 1,
    "mainnet_income_put_btc": 1,
    "mainnet_income_put_mngo": 1,
    "mainnet_income_call_sbr": 1,
    "mainnet_income_call_luna": 1,
    "mainnet_income_call_socean": 1,
    "mainnet_income_call_sol": 1.02193,
    "mainnet_income_call_marinade": 1.01091,
    "mainnet_income_call_btc": 1.05125,
    "mainnet_income_call_eth": 1.006,
    "mainnet_income_call_ftt": 1,
    "mainnet_income_call_srm": 1,
    "mainnet_income_call_mngo": 1
  }
}