{
  "totalTvlUSD": 112582344.54,
  "coinsByCoingeckoId": {
    "solana": 171404.91977887,
    "msol": 162659.600085918,
    "bitcoin": 426.921418,
    "saber": 19999999.49755,
    "ftx-token": 73198.452582,
    "terra-luna": 84185.383399,
    "terrausd": 94906.30825,
    "usd-coin": 13005680.302149998,
    "socean-staked-sol": 10999.997467117,
    "serum": 4206088.666981,
    "mango-markets": 9017414.639675,
    "raydium": 19967.02804,
    "ethereum": 1748.154102
  },
  "pricesByCoingeckoId": {
    "BTC": 42290,
    "SOL": 140.41,
    "ETH": 3218.4,
    "mSOL": 144.31,
    "FTT": 44.59,
    "SRM": 3.02,
    "USDC": 1,
    "MNGO": 0.198925,
    "scnSOL": 143.65,
    "SBR": 0.113546,
    "LUNA": 77.76,
    "UST": 0.999682,
    "RAY": 5.17
  },
  "sharePricesByGlobalId": {
    "mainnet_income_call_sol": 1.04444,
    "mainnet_income_call_marinade": 1.03017,
    "mainnet_income_call_btc": 1.06814,
    "mainnet_income_call_sbr": 1.04667,
    "mainnet_income_call_ftt": 1.02068,
    "mainnet_income_call_luna": 1.02692,
    "mainnet_income_put_luna": 1,
    "mainnet_income_put_mngo": 1.00201,
    "mainnet_income_call_socean": 1.01629,
    "mainnet_income_call_srm": 1.01304,
    "mainnet_income_call_mngo": 1.01322,
    "mainnet_income_call_ray": 1.00275,
    "mainnet_income_call_eth": 1.01502,
    "mainnet_income_put_sol": 1.00281,
    "mainnet_income_put_btc": 1.00329
  },
  "depositTokenByGlobalId": {
    "mainnet_income_call_sol": 171404.91977887,
    "mainnet_income_call_marinade": 162659.600085918,
    "mainnet_income_call_btc": 426.921418,
    "mainnet_income_call_sbr": 19999999.49755,
    "mainnet_income_call_ftt": 73198.452582,
    "mainnet_income_call_luna": 84185.383399,
    "mainnet_income_put_luna": 94906.30825,
    "mainnet_income_put_mngo": 397676.27,
    "mainnet_income_call_socean": 10999.997467117,
    "mainnet_income_call_srm": 4206088.666981,
    "mainnet_income_call_mngo": 9017414.639675,
    "mainnet_income_call_ray": 19967.02804,
    "mainnet_income_call_eth": 1748.154102,
    "mainnet_income_put_sol": 11482228,
    "mainnet_income_put_btc": 1125776.04
  },
  "usdValueByGlobalId": {
    "mainnet_income_call_sol": 24066964.79,
    "mainnet_income_call_marinade": 23473406.89,
    "mainnet_income_call_btc": 18054506.77,
    "mainnet_income_call_sbr": 2270919.94,
    "mainnet_income_call_ftt": 3263919,
    "mainnet_income_call_luna": 6546255.41,
    "mainnet_income_put_luna": 94876.13,
    "mainnet_income_put_mngo": 397676.27,
    "mainnet_income_call_socean": 1580149.64,
    "mainnet_income_call_srm": 12702387.77,
    "mainnet_income_call_mngo": 1793789.21,
    "mainnet_income_call_ray": 103229.53,
    "mainnet_income_call_eth": 5626259.16,
    "mainnet_income_put_sol": 11482228,
    "mainnet_income_put_btc": 1125776.04
  },
  "globalIdToDepositTokenCoingeckoId": {
    "mainnet_income_call_sol": "solana",
    "mainnet_income_call_marinade": "msol",
    "mainnet_income_call_btc": "bitcoin",
    "mainnet_income_call_sbr": "saber",
    "mainnet_income_call_ftt": "ftx-token",
    "mainnet_income_call_luna": "terra-luna",
    "mainnet_income_put_luna": "terrausd",
    "mainnet_income_put_mngo": "usd-coin",
    "mainnet_income_call_socean": "socean-staked-sol",
    "mainnet_income_call_srm": "serum",
    "mainnet_income_call_mngo": "mango-markets",
    "mainnet_income_call_ray": "raydium",
    "mainnet_income_call_eth": "ethereum",
    "mainnet_income_put_sol": "usd-coin",
    "mainnet_income_put_btc": "usd-coin"
  }
}