{
  "totalTvlUSD": 102574798.57,
  "coinsByCoingeckoId": {
    "solana": 137034.837759574,
    "msol": 146322.025962925,
    "bitcoin": 371.518574,
    "saber": 11309919.04627,
    "ftx-token": 76697.451325,
    "usd-coin": 14048364.486025,
    "terra-luna": 60175.713411,
    "socean-staked-sol": 8581.183384271,
    "serum": 3976533.073675,
    "mango-markets": 6019474.318135,
    "raydium": 19310.493998,
    "ethereum": 1493.006766
  },
  "pricesByCoingeckoId": {
    "BTC": 43720,
    "SOL": 149.36,
    "ETH": 3352.19,
    "mSOL": 153.49,
    "FTT": 41.21,
    "SRM": 3.19,
    "USDC": 1,
    "MNGO": 0.210229,
    "scnSOL": 152.27,
    "SBR": 0.084093,
    "LUNA": 81.05,
    "RAY": 5.49
  },
  "sharePricesByGlobalId": {
    "mainnet_income_call_sol": 1.03708,
    "mainnet_income_call_marinade": 1.02581,
    "mainnet_income_call_btc": 1.0644,
    "mainnet_income_call_sbr": 1,
    "mainnet_income_call_ftt": 1.01481,
    "mainnet_income_put_mngo": 1,
    "mainnet_income_call_luna": 1.01873,
    "mainnet_income_call_socean": 1.01266,
    "mainnet_income_call_srm": 1.00834,
    "mainnet_income_call_mngo": 1.01232,
    "mainnet_income_call_ray": 1,
    "mainnet_income_call_eth": 1.01181,
    "mainnet_income_put_sol": 0.99999,
    "mainnet_income_put_btc": 1
  },
  "depositTokenByGlobalId": {
    "mainnet_income_call_sol": 137034.837759574,
    "mainnet_income_call_marinade": 146322.025962925,
    "mainnet_income_call_btc": 371.518574,
    "mainnet_income_call_sbr": 11309919.04627,
    "mainnet_income_call_ftt": 76697.451325,
    "mainnet_income_put_mngo": 429804.43,
    "mainnet_income_call_luna": 60175.713411,
    "mainnet_income_call_socean": 8581.183384271,
    "mainnet_income_call_srm": 3976533.073675,
    "mainnet_income_call_mngo": 6019474.318135,
    "mainnet_income_call_ray": 19310.493998,
    "mainnet_income_call_eth": 1493.006766,
    "mainnet_income_put_sol": 11264172.26,
    "mainnet_income_put_btc": 2354387.79
  },
  "usdValueByGlobalId": {
    "mainnet_income_call_sol": 20467523.37,
    "mainnet_income_call_marinade": 22458967.77,
    "mainnet_income_call_btc": 16242792.06,
    "mainnet_income_call_sbr": 951085.02,
    "mainnet_income_call_ftt": 3160701.97,
    "mainnet_income_put_mngo": 429804.43,
    "mainnet_income_call_luna": 4877241.57,
    "mainnet_income_call_socean": 1306656.79,
    "mainnet_income_call_srm": 12685140.51,
    "mainnet_income_call_mngo": 1265468.07,
    "mainnet_income_call_ray": 106014.61,
    "mainnet_income_call_eth": 5004842.35,
    "mainnet_income_put_sol": 11264172.26,
    "mainnet_income_put_btc": 2354387.79
  }
}