{
  "totalTvlUSD": 91483709.5,
  "coinsByCoingeckoId": {
    "solana": 113277.769203016,
    "msol": 122235.429623935,
    "bitcoin": 329.45613,
    "raydium": 18765.03449,
    "ethereum": 1390.675916,
    "ftx-token": 69354.163678,
    "usd-coin": 10937187.864355,
    "saber": 11000000,
    "terra-luna": 29999.962273,
    "socean-staked-sol": 5499.999932776,
    "serum": 3936806.132181,
    "mango-markets": 5999999.877036
  },
  "pricesByCoingeckoId": {
    "BTC": 44859,
    "SOL": 158.02,
    "ETH": 3667.42,
    "mSOL": 162.69,
    "FTT": 39.98,
    "SRM": 3.57,
    "USDC": 1,
    "MNGO": 0.227639,
    "scnSOL": 162.74,
    "SBR": 0.117535,
    "LUNA": 79.35,
    "RAY": 6.35
  },
  "sharePricesByGlobalId": {
    "mainnet_income_call_sol": 1.03196,
    "mainnet_income_call_marinade": 1.0226,
    "mainnet_income_call_btc": 1.05863,
    "mainnet_income_call_ray": 1,
    "mainnet_income_call_eth": 1.006,
    "mainnet_income_call_ftt": 1,
    "mainnet_income_put_mngo": 1,
    "mainnet_income_call_sbr": 1,
    "mainnet_income_call_luna": 1,
    "mainnet_income_call_socean": 1,
    "mainnet_income_call_srm": 1,
    "mainnet_income_call_mngo": 1,
    "mainnet_income_put_sol": 1,
    "mainnet_income_put_btc": 1
  },
  "depositTokenByGlobalId": {
    "mainnet_income_call_sol": 113277.769203016,
    "mainnet_income_call_marinade": 122235.429623935,
    "mainnet_income_call_btc": 329.45613,
    "mainnet_income_call_ray": 18765.03449,
    "mainnet_income_call_eth": 1390.675916,
    "mainnet_income_call_ftt": 69354.163678,
    "mainnet_income_put_mngo": 272000.65,
    "mainnet_income_call_sbr": 11000000,
    "mainnet_income_call_luna": 29999.962273,
    "mainnet_income_call_socean": 5499.999932776,
    "mainnet_income_call_srm": 3936806.132181,
    "mainnet_income_call_mngo": 5999999.877036,
    "mainnet_income_put_sol": 8235670.78,
    "mainnet_income_put_btc": 2429516.44
  },
  "usdValueByGlobalId": {
    "mainnet_income_call_sol": 17900153.09,
    "mainnet_income_call_marinade": 19886482.05,
    "mainnet_income_call_btc": 14779072.54,
    "mainnet_income_call_ray": 119157.97,
    "mainnet_income_call_eth": 5100192.67,
    "mainnet_income_call_ftt": 2772779.46,
    "mainnet_income_put_mngo": 272000.65,
    "mainnet_income_call_sbr": 1292885,
    "mainnet_income_call_luna": 2380497.01,
    "mainnet_income_call_socean": 895069.99,
    "mainnet_income_call_srm": 14054397.89,
    "mainnet_income_call_mngo": 1365833.97,
    "mainnet_income_put_sol": 8235670.78,
    "mainnet_income_put_btc": 2429516.44
  }
}