{
  "totalTvlUSD": 102992353.84,
  "coinsByCoingeckoId": {
    "solana": 137064.502759574,
    "msol": 146331.097551439,
    "bitcoin": 371.518676,
    "saber": 11324226.74722,
    "ftx-token": 76697.451325,
    "usd-coin": 14048571.486025,
    "terra-luna": 60181.223411,
    "socean-staked-sol": 8581.183384271,
    "serum": 3977065.002144,
    "mango-markets": 6020584.877999,
    "raydium": 19310.493998,
    "ethereum": 1493.006786
  },
  "pricesByCoingeckoId": {
    "BTC": 43856,
    "SOL": 150.68,
    "ETH": 3353.12,
    "mSOL": 154.07,
    "FTT": 41.55,
    "SRM": 3.21,
    "USDC": 1,
    "MNGO": 0.208391,
    "scnSOL": 152.34,
    "SBR": 0.084368,
    "LUNA": 80.91,
    "RAY": 5.51
  },
  "sharePricesByGlobalId": {
    "mainnet_income_call_sol": 1.03708,
    "mainnet_income_call_marinade": 1.02581,
    "mainnet_income_call_btc": 1.0644,
    "mainnet_income_call_sbr": 1,
    "mainnet_income_call_ftt": 1.01481,
    "mainnet_income_put_mngo": 1,
    "mainnet_income_call_luna": 1.01873,
    "mainnet_income_call_socean": 1.01266,
    "mainnet_income_call_srm": 1.00834,
    "mainnet_income_call_mngo": 1.01232,
    "mainnet_income_call_ray": 1,
    "mainnet_income_call_eth": 1.01181,
    "mainnet_income_put_sol": 0.99999,
    "mainnet_income_put_btc": 1
  },
  "depositTokenByGlobalId": {
    "mainnet_income_call_sol": 137064.502759574,
    "mainnet_income_call_marinade": 146331.097551439,
    "mainnet_income_call_btc": 371.518676,
    "mainnet_income_call_sbr": 11324226.74722,
    "mainnet_income_call_ftt": 76697.451325,
    "mainnet_income_put_mngo": 429804.43,
    "mainnet_income_call_luna": 60181.223411,
    "mainnet_income_call_socean": 8581.183384271,
    "mainnet_income_call_srm": 3977065.002144,
    "mainnet_income_call_mngo": 6020584.877999,
    "mainnet_income_call_ray": 19310.493998,
    "mainnet_income_call_eth": 1493.006786,
    "mainnet_income_put_sol": 11264379.26,
    "mainnet_income_put_btc": 2354387.79
  },
  "usdValueByGlobalId": {
    "mainnet_income_call_sol": 20652879.28,
    "mainnet_income_call_marinade": 22545232.2,
    "mainnet_income_call_btc": 16293323.05,
    "mainnet_income_call_sbr": 955402.36,
    "mainnet_income_call_ftt": 3186779.1,
    "mainnet_income_put_mngo": 429804.43,
    "mainnet_income_call_luna": 4869262.79,
    "mainnet_income_call_socean": 1307257.48,
    "mainnet_income_call_srm": 12766378.66,
    "mainnet_income_call_mngo": 1254635.7,
    "mainnet_income_call_ray": 106400.82,
    "mainnet_income_call_eth": 5006230.91,
    "mainnet_income_put_sol": 11264379.26,
    "mainnet_income_put_btc": 2354387.79
  }
}