{
  "totalTvlUSD": 90879881.18,
  "coinsByCoingeckoId": {
    "solana": 128543.339350644,
    "msol": 136285.779588571,
    "bitcoin": 355.172859,
    "saber": 11000000,
    "ftx-token": 72608.061089,
    "usd-coin": 12776908.253459001,
    "terra-luna": 39999.999397,
    "socean-staked-sol": 5499.990099232,
    "serum": 3966278.475828,
    "mango-markets": 5999999.159277,
    "raydium": 18918.099566,
    "ethereum": 1433.050411
  },
  "pricesByCoingeckoId": {
    "BTC": 41934,
    "SOL": 142.38,
    "ETH": 3136.1,
    "mSOL": 146.07,
    "FTT": 36.2,
    "SRM": 3.04,
    "USDC": 1,
    "MNGO": 0.191058,
    "scnSOL": 145.69,
    "SBR": 0.091958,
    "LUNA": 68.99,
    "RAY": 5.34
  },
  "sharePricesByGlobalId": {
    "mainnet_income_call_sol": 1.03708,
    "mainnet_income_call_marinade": 1.02581,
    "mainnet_income_call_btc": 1.0644,
    "mainnet_income_call_sbr": 1,
    "mainnet_income_call_ftt": 1.01481,
    "mainnet_income_put_mngo": 1,
    "mainnet_income_call_luna": 1.01873,
    "mainnet_income_call_socean": 1.01266,
    "mainnet_income_call_srm": 1.00834,
    "mainnet_income_call_mngo": 1.01232,
    "mainnet_income_call_ray": 1,
    "mainnet_income_call_eth": 1.01181,
    "mainnet_income_put_sol": 1,
    "mainnet_income_put_btc": 1
  },
  "depositTokenByGlobalId": {
    "mainnet_income_call_sol": 128543.339350644,
    "mainnet_income_call_marinade": 136285.779588571,
    "mainnet_income_call_btc": 355.172859,
    "mainnet_income_call_sbr": 11000000,
    "mainnet_income_call_ftt": 72608.061089,
    "mainnet_income_put_mngo": 424829.63,
    "mainnet_income_call_luna": 39999.999397,
    "mainnet_income_call_socean": 5499.990099232,
    "mainnet_income_call_srm": 3966278.475828,
    "mainnet_income_call_mngo": 5999999.159277,
    "mainnet_income_call_ray": 18918.099566,
    "mainnet_income_call_eth": 1433.050411,
    "mainnet_income_put_sol": 9999999.97,
    "mainnet_income_put_btc": 2352078.65
  },
  "usdValueByGlobalId": {
    "mainnet_income_call_sol": 18302000.66,
    "mainnet_income_call_marinade": 19907263.82,
    "mainnet_income_call_btc": 14893818.67,
    "mainnet_income_call_sbr": 1011538,
    "mainnet_income_call_ftt": 2628411.81,
    "mainnet_income_put_mngo": 424829.63,
    "mainnet_income_call_luna": 2759599.96,
    "mainnet_income_call_socean": 801293.56,
    "mainnet_income_call_srm": 12057486.57,
    "mainnet_income_call_mngo": 1146347.84,
    "mainnet_income_call_ray": 101022.65,
    "mainnet_income_call_eth": 4494189.39,
    "mainnet_income_put_sol": 9999999.97,
    "mainnet_income_put_btc": 2352078.65
  }
}