{
  "totalTvlUSD": 46524740.04,
  "coinsByCoingeckoId": {
    "usd-coin": 11434.210879,
    "solana": 83999.381153664,
    "msol": 84999.999912832,
    "bitcoin": 205.369725,
    "ethereum": 367.877862,
    "ftx-token": 24835.99047,
    "serum": 212946.388251,
    "mango-markets": 1599404.648688
  },
  "pricesByCoingeckoId": {
    "BTC": 49463,
    "SOL": 191.28,
    "ETH": 3933.08,
    "mSOL": 195.22,
    "FTT": 40.88,
    "SRM": 3.87,
    "USDC": 1,
    "MNGO": 0.254914
  },
  "sharePricesByGlobalId": {
    "mainnet_income_put_sol": 1,
    "mainnet_income_put_btc": 1,
    "mainnet_income_put_mngo": 1,
    "mainnet_income_call_sol": 1.02193,
    "mainnet_income_call_marinade": 1.01091,
    "mainnet_income_call_btc": 1.05125,
    "mainnet_income_call_eth": 1.006,
    "mainnet_income_call_ftt": 1,
    "mainnet_income_call_srm": 1,
    "mainnet_income_call_mngo": 1
  }
}