{
  "totalTvlUSD": 67120078.09,
  "coinsByCoingeckoId": {
    "usd-coin": 5727875.661901,
    "saber": 10999999.811266,
    "terra-luna": 9999.429376,
    "socean-staked-sol": 5499.994393146,
    "solana": 83999.999119664,
    "msol": 84999.999912832,
    "bitcoin": 279.109664,
    "ethereum": 585.955472,
    "ftx-token": 28848.108048,
    "serum": 3458959.704526,
    "mango-markets": 2279610.715003
  },
  "pricesByCoingeckoId": {
    "BTC": 47396,
    "SOL": 170.97,
    "ETH": 3749.4,
    "mSOL": 175.38,
    "FTT": 39.31,
    "SRM": 3.48,
    "USDC": 1,
    "MNGO": 0.21746,
    "scnSOL": 174.91,
    "SBR": 0.109162,
    "LUNA": 86.81
  },
  "sharePricesByGlobalId": {
    "mainnet_income_put_sol": 1,
    "mainnet_income_put_btc": 1,
    "mainnet_income_put_mngo": 1,
    "mainnet_income_call_sbr": 1,
    "mainnet_income_call_luna": 1,
    "mainnet_income_call_socean": 1,
    "mainnet_income_call_sol": 1.02193,
    "mainnet_income_call_marinade": 1.01091,
    "mainnet_income_call_btc": 1.05125,
    "mainnet_income_call_eth": 1.006,
    "mainnet_income_call_ftt": 1,
    "mainnet_income_call_srm": 1,
    "mainnet_income_call_mngo": 1
  }
}