{
  "totalTvlUSD": 112189880.28,
  "coinsByCoingeckoId": {
    "solana": 169502.13577887,
    "msol": 162362.816101355,
    "bitcoin": 426.70742,
    "saber": 19999999.49755,
    "ftx-token": 73187.495643,
    "terra-luna": 83071.872029,
    "terrausd": 94851.30825,
    "usd-coin": 12976418.534026999,
    "socean-staked-sol": 10999.997467117,
    "serum": 4206063.366981,
    "mango-markets": 9011579.496596,
    "raydium": 19590.804604,
    "ethereum": 1745.385409
  },
  "pricesByCoingeckoId": {
    "BTC": 42320,
    "SOL": 140.12,
    "ETH": 3224.84,
    "mSOL": 143.55,
    "FTT": 45.09,
    "SRM": 3.01,
    "USDC": 1,
    "MNGO": 0.199105,
    "scnSOL": 142.78,
    "SBR": 0.115828,
    "LUNA": 79.82,
    "UST": 1,
    "RAY": 5.18
  },
  "sharePricesByGlobalId": {
    "mainnet_income_call_sol": 1.04444,
    "mainnet_income_call_marinade": 1.03017,
    "mainnet_income_call_btc": 1.06814,
    "mainnet_income_call_sbr": 1.04667,
    "mainnet_income_call_ftt": 1.02068,
    "mainnet_income_call_luna": 1.02692,
    "mainnet_income_put_luna": 1,
    "mainnet_income_put_mngo": 1.00201,
    "mainnet_income_call_socean": 1.01629,
    "mainnet_income_call_srm": 1.01304,
    "mainnet_income_call_mngo": 1.01322,
    "mainnet_income_call_ray": 1.00275,
    "mainnet_income_call_eth": 1.01502,
    "mainnet_income_put_sol": 1.00281,
    "mainnet_income_put_btc": 1.00329
  },
  "depositTokenByGlobalId": {
    "mainnet_income_call_sol": 169502.13577887,
    "mainnet_income_call_marinade": 162362.816101355,
    "mainnet_income_call_btc": 426.70742,
    "mainnet_income_call_sbr": 19999999.49755,
    "mainnet_income_call_ftt": 73187.495643,
    "mainnet_income_call_luna": 83071.872029,
    "mainnet_income_put_luna": 94851.30825,
    "mainnet_income_put_mngo": 397676.27,
    "mainnet_income_call_socean": 10999.997467117,
    "mainnet_income_call_srm": 4206063.366981,
    "mainnet_income_call_mngo": 9011579.496596,
    "mainnet_income_call_ray": 19590.804604,
    "mainnet_income_call_eth": 1745.385409,
    "mainnet_income_put_sol": 11452966.23,
    "mainnet_income_put_btc": 1125776.04
  },
  "usdValueByGlobalId": {
    "mainnet_income_call_sol": 23750639.27,
    "mainnet_income_call_marinade": 23307182.25,
    "mainnet_income_call_btc": 18058258.01,
    "mainnet_income_call_sbr": 2316559.94,
    "mainnet_income_call_ftt": 3300024.18,
    "mainnet_income_call_luna": 6630796.83,
    "mainnet_income_put_luna": 94851.31,
    "mainnet_income_put_mngo": 397676.27,
    "mainnet_income_call_socean": 1570579.64,
    "mainnet_income_call_srm": 12660250.73,
    "mainnet_income_call_mngo": 1794250.54,
    "mainnet_income_call_ray": 101480.37,
    "mainnet_income_call_eth": 5628588.68,
    "mainnet_income_put_sol": 11452966.23,
    "mainnet_income_put_btc": 1125776.04
  },
  "globalIdToDepositTokenCoingeckoId": {
    "mainnet_income_call_sol": "solana",
    "mainnet_income_call_marinade": "msol",
    "mainnet_income_call_btc": "bitcoin",
    "mainnet_income_call_sbr": "saber",
    "mainnet_income_call_ftt": "ftx-token",
    "mainnet_income_call_luna": "terra-luna",
    "mainnet_income_put_luna": "terrausd",
    "mainnet_income_put_mngo": "usd-coin",
    "mainnet_income_call_socean": "socean-staked-sol",
    "mainnet_income_call_srm": "serum",
    "mainnet_income_call_mngo": "mango-markets",
    "mainnet_income_call_ray": "raydium",
    "mainnet_income_call_eth": "ethereum",
    "mainnet_income_put_sol": "usd-coin",
    "mainnet_income_put_btc": "usd-coin"
  }
}