{
  "totalTvlUSD": 59672600.75,
  "coinsByCoingeckoId": {
    "usd-coin": 1145266.901259,
    "saber": 5298302.322602,
    "terra-luna": 8882.165049,
    "socean-staked-sol": 2292.17359188,
    "solana": 83999.999119664,
    "msol": 84999.999912832,
    "bitcoin": 247.070799,
    "ethereum": 474.69579,
    "ftx-token": 27551.001675,
    "serum": 3452766.029635,
    "mango-markets": 2046342.397052
  },
  "pricesByCoingeckoId": {
    "BTC": 47210,
    "SOL": 174.17,
    "ETH": 3719.95,
    "mSOL": 178.44,
    "FTT": 40.16,
    "SRM": 3.49,
    "USDC": 1,
    "MNGO": 0.215659,
    "scnSOL": 177.84,
    "SBR": 0.100166,
    "LUNA": 85.94
  },
  "sharePricesByGlobalId": {
    "mainnet_income_put_sol": 1,
    "mainnet_income_put_btc": 1,
    "mainnet_income_put_mngo": 1,
    "mainnet_income_call_sbr": 1,
    "mainnet_income_call_luna": 1,
    "mainnet_income_call_socean": 1,
    "mainnet_income_call_sol": 1.02193,
    "mainnet_income_call_marinade": 1.01091,
    "mainnet_income_call_btc": 1.05125,
    "mainnet_income_call_eth": 1.006,
    "mainnet_income_call_ftt": 1,
    "mainnet_income_call_srm": 1,
    "mainnet_income_call_mngo": 1
  }
}