{
  "totalTvlUSD": 106671401.73,
  "coinsByCoingeckoId": {
    "solana": 140711.09111187,
    "msol": 158783.555876085,
    "bitcoin": 416.715146,
    "saber": 19999847.492037,
    "ftx-token": 67263.452173,
    "usd-coin": 12008082.023302,
    "terra-luna": 67075.420731,
    "socean-staked-sol": 10999.987641614,
    "serum": 4059672.252408,
    "mango-markets": 8713377.314498,
    "raydium": 16338.626813,
    "ethereum": 1688.539982
  },
  "pricesByCoingeckoId": {
    "BTC": 43146,
    "SOL": 145.92,
    "ETH": 3325.31,
    "mSOL": 149.85,
    "FTT": 45.29,
    "SRM": 3.21,
    "USDC": 1,
    "MNGO": 0.199123,
    "scnSOL": 149.25,
    "SBR": 0.08503,
    "LUNA": 81.99,
    "RAY": 5.37
  },
  "sharePricesByGlobalId": {
    "mainnet_income_call_sol": 1.04444,
    "mainnet_income_call_marinade": 1.03017,
    "mainnet_income_call_btc": 1.06814,
    "mainnet_income_call_sbr": 1.04667,
    "mainnet_income_call_ftt": 1.02068,
    "mainnet_income_put_mngo": 1.00201,
    "mainnet_income_call_luna": 1.02692,
    "mainnet_income_call_socean": 1.01629,
    "mainnet_income_call_srm": 1.01304,
    "mainnet_income_call_mngo": 1.01322,
    "mainnet_income_call_ray": 1.00275,
    "mainnet_income_call_eth": 1.01502,
    "mainnet_income_put_sol": 1.00281,
    "mainnet_income_put_btc": 1.00329
  },
  "depositTokenByGlobalId": {
    "mainnet_income_call_sol": 140711.09111187,
    "mainnet_income_call_marinade": 158783.555876085,
    "mainnet_income_call_btc": 416.715146,
    "mainnet_income_call_sbr": 19999847.492037,
    "mainnet_income_call_ftt": 67263.452173,
    "mainnet_income_put_mngo": 392112.07,
    "mainnet_income_call_luna": 67075.420731,
    "mainnet_income_call_socean": 10999.987641614,
    "mainnet_income_call_srm": 4059672.252408,
    "mainnet_income_call_mngo": 8713377.314498,
    "mainnet_income_call_ray": 16338.626813,
    "mainnet_income_call_eth": 1688.539982,
    "mainnet_income_put_sol": 10491485.82,
    "mainnet_income_put_btc": 1124484.14
  },
  "usdValueByGlobalId": {
    "mainnet_income_call_sol": 20532562.42,
    "mainnet_income_call_marinade": 23793715.85,
    "mainnet_income_call_btc": 17979591.69,
    "mainnet_income_call_sbr": 1700587.03,
    "mainnet_income_call_ftt": 3046361.75,
    "mainnet_income_put_mngo": 392112.07,
    "mainnet_income_call_luna": 5499513.75,
    "mainnet_income_call_socean": 1641748.16,
    "mainnet_income_call_srm": 13031547.93,
    "mainnet_income_call_mngo": 1735033.83,
    "mainnet_income_call_ray": 87738.43,
    "mainnet_income_call_eth": 5614918.89,
    "mainnet_income_put_sol": 10491485.82,
    "mainnet_income_put_btc": 1124484.14
  },
  "globalIdToDepositTokenCoingeckoId": {
    "mainnet_income_call_sol": "solana",
    "mainnet_income_call_marinade": "msol",
    "mainnet_income_call_btc": "bitcoin",
    "mainnet_income_call_sbr": "saber",
    "mainnet_income_call_ftt": "ftx-token",
    "mainnet_income_put_mngo": "usd-coin",
    "mainnet_income_call_luna": "terra-luna",
    "mainnet_income_call_socean": "socean-staked-sol",
    "mainnet_income_call_srm": "serum",
    "mainnet_income_call_mngo": "mango-markets",
    "mainnet_income_call_ray": "raydium",
    "mainnet_income_call_eth": "ethereum",
    "mainnet_income_put_sol": "usd-coin",
    "mainnet_income_put_btc": "usd-coin"
  }
}