{
  "totalTvlUSD": 92464085.68,
  "coinsByCoingeckoId": {
    "solana": 131986.757759574,
    "msol": 142484.521766837,
    "bitcoin": 366.149309,
    "saber": 11000000,
    "ftx-token": 76146.793877,
    "usd-coin": 13046686.358778,
    "terra-luna": 54844.5109,
    "socean-staked-sol": 6954.270941025,
    "serum": 3974334.558091,
    "mango-markets": 5999999.159277,
    "raydium": 19194.149433,
    "ethereum": 1479.616665
  },
  "pricesByCoingeckoId": {
    "BTC": 42058,
    "SOL": 136.33,
    "ETH": 3107.88,
    "mSOL": 139.32,
    "FTT": 38.21,
    "SRM": 2.93,
    "USDC": 1,
    "MNGO": 0.19652,
    "scnSOL": 138.42,
    "SBR": 0.075747,
    "LUNA": 71.98,
    "RAY": 5.09
  },
  "sharePricesByGlobalId": {
    "mainnet_income_call_sol": 1.03708,
    "mainnet_income_call_marinade": 1.02581,
    "mainnet_income_call_btc": 1.0644,
    "mainnet_income_call_sbr": 1,
    "mainnet_income_call_ftt": 1.01481,
    "mainnet_income_put_mngo": 1.00062,
    "mainnet_income_call_luna": 1.01873,
    "mainnet_income_call_socean": 1.01266,
    "mainnet_income_call_srm": 1.00834,
    "mainnet_income_call_mngo": 1.01232,
    "mainnet_income_call_ray": 1,
    "mainnet_income_call_eth": 1.01181,
    "mainnet_income_put_sol": 1.00376,
    "mainnet_income_put_btc": 1
  },
  "depositTokenByGlobalId": {
    "mainnet_income_call_sol": 131986.757759574,
    "mainnet_income_call_marinade": 142484.521766837,
    "mainnet_income_call_btc": 366.149309,
    "mainnet_income_call_sbr": 11000000,
    "mainnet_income_call_ftt": 76146.793877,
    "mainnet_income_put_mngo": 429058.15,
    "mainnet_income_call_luna": 54844.5109,
    "mainnet_income_call_socean": 6954.270941025,
    "mainnet_income_call_srm": 3974334.558091,
    "mainnet_income_call_mngo": 5999999.159277,
    "mainnet_income_call_ray": 19194.149433,
    "mainnet_income_call_eth": 1479.616665,
    "mainnet_income_put_sol": 10263250.42,
    "mainnet_income_put_btc": 2354377.79
  },
  "usdValueByGlobalId": {
    "mainnet_income_call_sol": 17993754.69,
    "mainnet_income_call_marinade": 19850943.57,
    "mainnet_income_call_btc": 15399507.64,
    "mainnet_income_call_sbr": 833217,
    "mainnet_income_call_ftt": 2909568.99,
    "mainnet_income_put_mngo": 429058.15,
    "mainnet_income_call_luna": 3947707.89,
    "mainnet_income_call_socean": 962610.18,
    "mainnet_income_call_srm": 11644800.26,
    "mainnet_income_call_mngo": 1179119.83,
    "mainnet_income_call_ray": 97698.22,
    "mainnet_income_call_eth": 4598471.04,
    "mainnet_income_put_sol": 10263250.42,
    "mainnet_income_put_btc": 2354377.79
  }
}