{
  "totalTvlUSD": 72888464.88,
  "coinsByCoingeckoId": {
    "solana": 83999.980763016,
    "msol": 84999.956032314,
    "bitcoin": 311.140017,
    "ethereum": 794.537354,
    "ftx-token": 41230.207156,
    "usd-coin": 6483777.964381,
    "saber": 11000000,
    "terra-luna": 9999.995722,
    "socean-staked-sol": 5499.999393146,
    "serum": 3863846.441361,
    "mango-markets": 2384520.351195
  },
  "pricesByCoingeckoId": {
    "BTC": 47218,
    "SOL": 173.05,
    "ETH": 3729.53,
    "mSOL": 177.32,
    "FTT": 39.36,
    "SRM": 3.54,
    "USDC": 1,
    "MNGO": 0.211042,
    "scnSOL": 176.73,
    "SBR": 0.135032,
    "LUNA": 88.02
  },
  "sharePricesByGlobalId": {
    "mainnet_income_call_sol": 1.03196,
    "mainnet_income_call_marinade": 1.0226,
    "mainnet_income_call_btc": 1.05863,
    "mainnet_income_call_eth": 1.006,
    "mainnet_income_call_ftt": 1,
    "mainnet_income_put_mngo": 1,
    "mainnet_income_call_sbr": 1,
    "mainnet_income_call_luna": 1,
    "mainnet_income_call_socean": 1,
    "mainnet_income_call_srm": 1,
    "mainnet_income_call_mngo": 1,
    "mainnet_income_put_sol": 1,
    "mainnet_income_put_btc": 1
  }
}