{
  "totalTvlUSD": 107735781.97,
  "coinsByCoingeckoId": {
    "solana": 142459.76811187,
    "msol": 159031.718566754,
    "bitcoin": 416.921288,
    "saber": 19999997.492037,
    "ftx-token": 67356.918789,
    "usd-coin": 12131653.003927,
    "terra-luna": 68172.638081,
    "socean-staked-sol": 10999.987641614,
    "serum": 4063633.368454,
    "mango-markets": 8818351.851856,
    "raydium": 16652.379413,
    "ethereum": 1697.302106
  },
  "pricesByCoingeckoId": {
    "BTC": 43217,
    "SOL": 146.46,
    "ETH": 3344.34,
    "mSOL": 150.24,
    "FTT": 46.71,
    "SRM": 3.2,
    "USDC": 1,
    "MNGO": 0.196643,
    "scnSOL": 149.9,
    "SBR": 0.086845,
    "LUNA": 84.96,
    "RAY": 5.43
  },
  "sharePricesByGlobalId": {
    "mainnet_income_call_sol": 1.04444,
    "mainnet_income_call_marinade": 1.03017,
    "mainnet_income_call_btc": 1.06814,
    "mainnet_income_call_sbr": 1.04667,
    "mainnet_income_call_ftt": 1.02068,
    "mainnet_income_put_mngo": 1.00201,
    "mainnet_income_call_luna": 1.02692,
    "mainnet_income_call_socean": 1.01629,
    "mainnet_income_call_srm": 1.01304,
    "mainnet_income_call_mngo": 1.01322,
    "mainnet_income_call_ray": 1.00275,
    "mainnet_income_call_eth": 1.01502,
    "mainnet_income_put_sol": 1.00281,
    "mainnet_income_put_btc": 1.00329
  },
  "depositTokenByGlobalId": {
    "mainnet_income_call_sol": 142459.76811187,
    "mainnet_income_call_marinade": 159031.718566754,
    "mainnet_income_call_btc": 416.921288,
    "mainnet_income_call_sbr": 19999997.492037,
    "mainnet_income_call_ftt": 67356.918789,
    "mainnet_income_put_mngo": 392112.07,
    "mainnet_income_call_luna": 68172.638081,
    "mainnet_income_call_socean": 10999.987641614,
    "mainnet_income_call_srm": 4063633.368454,
    "mainnet_income_call_mngo": 8818351.851856,
    "mainnet_income_call_ray": 16652.379413,
    "mainnet_income_call_eth": 1697.302106,
    "mainnet_income_put_sol": 10615056.8,
    "mainnet_income_put_btc": 1124484.14
  },
  "usdValueByGlobalId": {
    "mainnet_income_call_sol": 20864657.64,
    "mainnet_income_call_marinade": 23892925.4,
    "mainnet_income_call_btc": 18018087.3,
    "mainnet_income_call_sbr": 1736899.78,
    "mainnet_income_call_ftt": 3146241.68,
    "mainnet_income_put_mngo": 392112.07,
    "mainnet_income_call_luna": 5791947.33,
    "mainnet_income_call_socean": 1648898.15,
    "mainnet_income_call_srm": 13003626.78,
    "mainnet_income_call_mngo": 1734067.16,
    "mainnet_income_call_ray": 90422.42,
    "mainnet_income_call_eth": 5676355.33,
    "mainnet_income_put_sol": 10615056.8,
    "mainnet_income_put_btc": 1124484.14
  },
  "globalIdToDepositTokenCoingeckoId": {
    "mainnet_income_call_sol": "solana",
    "mainnet_income_call_marinade": "msol",
    "mainnet_income_call_btc": "bitcoin",
    "mainnet_income_call_sbr": "saber",
    "mainnet_income_call_ftt": "ftx-token",
    "mainnet_income_put_mngo": "usd-coin",
    "mainnet_income_call_luna": "terra-luna",
    "mainnet_income_call_socean": "socean-staked-sol",
    "mainnet_income_call_srm": "serum",
    "mainnet_income_call_mngo": "mango-markets",
    "mainnet_income_call_ray": "raydium",
    "mainnet_income_call_eth": "ethereum",
    "mainnet_income_put_sol": "usd-coin",
    "mainnet_income_put_btc": "usd-coin"
  }
}